agentrix/__init__.py
agentrix/cli.py
agentrix/core/__init__.py
agentrix/core/auth.py
agentrix/core/builder.py
agentrix/core/config.py
agentrix/core/dev_server.py
agentrix/core/inspector.py
agentrix/core/mcp_proxy.py
agentrix/core/mcp_sdk_proxy.py
agentrix/core/playground.py
agentrix/core/proxy.py
agentrix/core/registry.py
agentrix/core/server_manager.py
agentrix/models/__init__.py
agentrix/models/config.py
agentrix/models/server.py
agentrix/utils/__init__.py
agentrix/utils/logger.py
mcpmarket-0.1.6.dist-info/METADATA
mcpmarket-0.1.6.dist-info/WHEEL
mcpmarket-0.1.6.dist-info/entry_points.txt
mcpmarket-0.1.6.dist-info/licenses/LICENSE
mcpmarket-0.1.6.dist-info/RECORD
