Metadata-Version: 2.4
Name: mcpmarket
Version: 0.1.6
Summary: Python MCP server registry and proxy for AI agents
Project-URL: Documentation, https://github.com/xray918/agentrix
Project-URL: Issues, https://github.com/xray918/agentrix/issues
Project-URL: Source, https://github.com/xray918/agentrix
Project-URL: Repository, https://github.com/xray918/agentrix
Author-email: xray918 <xray918@github.com>
License-Expression: MIT
License-File: LICENSE
Keywords: agents,ai,mcp,proxy,registry
Classifier: Development Status :: 4 - Beta
Classifier: Intended Audience :: Developers
Classifier: License :: OSI Approved :: MIT License
Classifier: Operating System :: OS Independent
Classifier: Programming Language :: Python :: 3
Classifier: Programming Language :: Python :: 3.10
Classifier: Programming Language :: Python :: 3.11
Classifier: Programming Language :: Python :: 3.12
Classifier: Topic :: Scientific/Engineering :: Artificial Intelligence
Classifier: Topic :: Software Development :: Libraries :: Python Modules
Requires-Python: >=3.10
Requires-Dist: aiofiles>=23.0.0
Requires-Dist: anyio>=4.0.0
Requires-Dist: click>=8.1.0
Requires-Dist: httpx>=0.25.0
Requires-Dist: mcp>=1.0.0
Requires-Dist: packaging>=23.0
Requires-Dist: pydantic-settings>=2.1.0
Requires-Dist: pydantic>=2.5.0
Requires-Dist: rich>=13.0.0
Requires-Dist: tomlkit>=0.12.0
Requires-Dist: typer>=0.12.0
Requires-Dist: uvloop>=0.19.0; sys_platform != 'win32'
Provides-Extra: all
Requires-Dist: agentrix[dev,server]; extra == 'all'
Provides-Extra: dev
Requires-Dist: black>=23.0.0; extra == 'dev'
Requires-Dist: mypy>=1.7.0; extra == 'dev'
Requires-Dist: pre-commit>=3.0.0; extra == 'dev'
Requires-Dist: pytest-asyncio>=0.21.0; extra == 'dev'
Requires-Dist: pytest-cov>=4.0.0; extra == 'dev'
Requires-Dist: pytest>=7.0.0; extra == 'dev'
Requires-Dist: ruff>=0.1.0; extra == 'dev'
Provides-Extra: server
Requires-Dist: fastapi>=0.104.0; extra == 'server'
Requires-Dist: python-multipart>=0.0.6; extra == 'server'
Requires-Dist: uvicorn>=0.24.0; extra == 'server'
